brainpy/__init__.py
brainpy/check.py
brainpy/errors.py
brainpy/modes.py
brainpy/types.py
brainpy/algorithms/__init__.py
brainpy/algorithms/offline.py
brainpy/algorithms/online.py
brainpy/algorithms/utils.py
brainpy/analysis/__init__.py
brainpy/analysis/base.py
brainpy/analysis/constants.py
brainpy/analysis/stability.py
brainpy/analysis/highdim/__init__.py
brainpy/analysis/highdim/slow_points.py
brainpy/analysis/lowdim/__init__.py
brainpy/analysis/lowdim/lowdim_analyzer.py
brainpy/analysis/lowdim/lowdim_bifurcation.py
brainpy/analysis/lowdim/lowdim_phase_plane.py
brainpy/analysis/utils/__init__.py
brainpy/analysis/utils/function.py
brainpy/analysis/utils/measurement.py
brainpy/analysis/utils/model.py
brainpy/analysis/utils/optimization.py
brainpy/analysis/utils/others.py
brainpy/analysis/utils/outputs.py
brainpy/analysis/utils/visualization.py
brainpy/base/__init__.py
brainpy/base/base.py
brainpy/base/collector.py
brainpy/base/function.py
brainpy/base/io.py
brainpy/base/naming.py
brainpy/connect/__init__.py
brainpy/connect/base.py
brainpy/connect/custom_conn.py
brainpy/connect/random_conn.py
brainpy/connect/regular_conn.py
brainpy/datasets/__init__.py
brainpy/datasets/_internally_replaced_utils.py
brainpy/datasets/base.py
brainpy/datasets/chaos/__init__.py
brainpy/datasets/chaos/chaotic_systems.py
brainpy/datasets/vision/__init__.py
brainpy/datasets/vision/base.py
brainpy/datasets/vision/mnist.py
brainpy/datasets/vision/utils.py
brainpy/dyn/__init__.py
brainpy/dyn/base.py
brainpy/dyn/runners.py
brainpy/dyn/channels/Ca.py
brainpy/dyn/channels/IH.py
brainpy/dyn/channels/K.py
brainpy/dyn/channels/KCa.py
brainpy/dyn/channels/Na.py
brainpy/dyn/channels/__init__.py
brainpy/dyn/channels/base.py
brainpy/dyn/channels/leaky.py
brainpy/dyn/layers/__init__.py
brainpy/dyn/layers/conv.py
brainpy/dyn/layers/dropout.py
brainpy/dyn/layers/linear.py
brainpy/dyn/layers/normalization.py
brainpy/dyn/layers/nvar.py
brainpy/dyn/layers/pooling.py
brainpy/dyn/layers/reservoir.py
brain_py-2.1.20.dist-info/LICENSE
brain_py-2.1.20.dist-info/METADATA
brain_py-2.1.20.dist-info/WHEEL
brain_py-2.1.20.dist-info/top_level.txt
brain_py-2.1.20.dist-info/RECORD
