Metadata-Version: 2.1
Name: brain-py
Version: 2.1.20
Summary: BrainPy: Brain Dynamics Programming in Python
Home-page: https://github.com/PKU-NIP-Lab/BrainPy
Author: BrainPy Team
Author-email: chao.brain@qq.com
License: GPL-3.0 License
Project-URL: Bug Tracker, https://github.com/PKU-NIP-Lab/BrainPy/issues
Project-URL: Documentation, https://brainpy.readthedocs.io/
Project-URL: Source Code, https://github.com/PKU-NIP-Lab/BrainPy
Keywords: computational neuroscience,brain-inspired computation,dynamical systems,differential equations,brain modeling,brain dynamics programming
Platform: UNKNOWN
Classifier: Natural Language :: English
Classifier: Operating System :: OS Independent
Classifier: Programming Language :: Python
Classifier: Programming Language :: Python :: 3
Classifier: Programming Language :: Python :: 3.7
Classifier: Programming Language :: Python :: 3.8
Classifier: Programming Language :: Python :: 3.9
Classifier: Programming Language :: Python :: 3.10
Classifier: Intended Audience :: Science/Research
Classifier: License :: OSI Approved :: GNU General Public License v3 (GPLv3)
Classifier: Topic :: Scientific/Engineering :: Bio-Informatics
Classifier: Topic :: Scientific/Engineering :: Mathematics
Classifier: Topic :: Scientific/Engineering :: Artificial Intelligence
Classifier: Topic :: Software Development :: Libraries
Requires-Python: >=3.7
Requires-Dist: jax (>=0.3.0)
Requires-Dist: numpy (>=1.15)
Requires-Dist: tqdm
Provides-Extra: all
Requires-Dist: brainpylib (>=0.0.6) ; extra == 'all'
Requires-Dist: jaxlib (>=0.3.0) ; extra == 'all'
Requires-Dist: matplotlib ; extra == 'all'
Requires-Dist: numba (>=0.50) ; extra == 'all'
Requires-Dist: scipy (>=1.1.0) ; extra == 'all'
Provides-Extra: cpu
Requires-Dist: brainpylib (>=0.0.6) ; extra == 'cpu'
Requires-Dist: jaxlib (>=0.3.0) ; extra == 'cpu'
Provides-Extra: cuda
Requires-Dist: brainpylib (>=0.0.6) ; extra == 'cuda'
Requires-Dist: jaxlib (>=0.3.0) ; extra == 'cuda'
